clinker/__init__.py
clinker/align.py
clinker/classes.py
clinker/formatters.py
clinker/main.py
clinker/plot.py
clinker/plot/clinker.js
clinker/plot/clustermap.min.js
clinker/plot/d3.min.js
clinker/plot/index.html
clinker/plot/mock.json
clinker/plot/style.css
clinker-0.0.32.dist-info/licenses/LICENSE
clinker-0.0.32.dist-info/METADATA
clinker-0.0.32.dist-info/WHEEL
clinker-0.0.32.dist-info/entry_points.txt
clinker-0.0.32.dist-info/top_level.txt
clinker-0.0.32.dist-info/RECORD
