Metadata-Version: 2.4
Name: clinker
Version: 0.0.32
Home-page: https://github.com/gamcil/clinker
Author: Cameron Gilchrist
Classifier: Programming Language :: Python :: 3
Classifier: License :: OSI Approved :: MIT License
Classifier: Operating System :: OS Independent
Requires-Python: >=3.6
License-File: LICENSE
Requires-Dist: biopython>=1.80
Requires-Dist: numpy>=1.13.3
Requires-Dist: scipy>=1.3.3
Requires-Dist: disjoint-set>=0.7.1
Requires-Dist: gffutils
Dynamic: author
Dynamic: classifier
Dynamic: description
Dynamic: description-content-type
Dynamic: home-page
Dynamic: license-file
Dynamic: requires-dist
Dynamic: requires-python
